gabbia.py
gabbia-0.1.0.data/data/usr/share/man/man1/gabbia.1
gabbia-0.1.0.dist-info/entry_points.txt
gabbia-0.1.0.dist-info/LICENSE
gabbia-0.1.0.dist-info/WHEEL
gabbia-0.1.0.dist-info/METADATA
gabbia-0.1.0.dist-info/RECORD
